odoo9_addon_partner_multi_company-9.0.1.0.1-py2.7-nspkg.pth
odoo9_addon_partner_multi_company-9.0.1.0.1.dist-info/DESCRIPTION.rst
odoo9_addon_partner_multi_company-9.0.1.0.1.dist-info/METADATA
odoo9_addon_partner_multi_company-9.0.1.0.1.dist-info/RECORD
odoo9_addon_partner_multi_company-9.0.1.0.1.dist-info/WHEEL
odoo9_addon_partner_multi_company-9.0.1.0.1.dist-info/metadata.json
odoo9_addon_partner_multi_company-9.0.1.0.1.dist-info/namespace_packages.txt
odoo9_addon_partner_multi_company-9.0.1.0.1.dist-info/top_level.txt
odoo_addons/partner_multi_company/README.rst
odoo_addons/partner_multi_company/__init__.py
odoo_addons/partner_multi_company/__openerp__.py
odoo_addons/partner_multi_company/hooks.py
odoo_addons/partner_multi_company/i18n/de.po
odoo_addons/partner_multi_company/i18n/es.po
odoo_addons/partner_multi_company/i18n/fr.po
odoo_addons/partner_multi_company/models/__init__.py
odoo_addons/partner_multi_company/models/res_partner.py
odoo_addons/partner_multi_company/models/res_users.py
odoo_addons/partner_multi_company/static/description/icon.png
odoo_addons/partner_multi_company/tests/__init__.py
odoo_addons/partner_multi_company/tests/test_partner_multi_company.py
odoo_addons/partner_multi_company/views/res_partner_view.xml
