Metadata-Version: 2.0
Name: odoo9-addon-partner-multi-company
Version: 9.0.1.0.1
Summary: Select individually the partner visibility on each company
Home-page: UNKNOWN
Author: Tecnativa, Odoo Community Association (OCA)
Author-email: support@odoo-community.org
License: AGPL-3
Platform: UNKNOWN
Classifier: Programming Language :: Python
Classifier: Framework :: Odoo
Classifier: License :: OSI Approved :: GNU Affero General Public License v3
Requires-Python: ~=2.7
Requires-Dist: odoo (<9.1a,>=9.0a)
Requires-Dist: odoo9-addon-base-suspend-security
